OpenControl/__init__.py
OpenControl/_version.py
OpenControl/ADP_control/__init__.py
OpenControl/ADP_control/controller.py
OpenControl/ADP_control/system.py
OpenControl/ADP_control/testcase_linearSystem.py
OpenControl/classiccontrol/__init__.py
OpenControl/classiccontrol/bibo.py
OpenControl/classiccontrol/controller.py
OpenControl/classiccontrol/linearsystem.py
OpenControl/classiccontrol/observer.py
OpenControl/classiccontrol/utils.py
OpenControl/visualize/__init__.py
OpenControl/visualize/visualize.py
OpenControl-0.3.dist-info/LICENSE
OpenControl-0.3.dist-info/METADATA
OpenControl-0.3.dist-info/WHEEL
OpenControl-0.3.dist-info/top_level.txt
OpenControl-0.3.dist-info/RECORD
