Metadata-Version: 2.1
Name: OpenControl
Version: 0.3
Summary: A python control systems package
Home-page: https://opencontrol.readthedocs.io/en/latest/
Author: VNOpenAI
Author-email: phi9b2@gmail.com
License: UNKNOWN
Project-URL: Bug Tracker, https://github.com/VNOpenAI/OpenControl/issues
Platform: UNKNOWN
Classifier: Programming Language :: Python :: 3
Classifier: License :: OSI Approved :: MIT License
Classifier: Operating System :: OS Independent
Requires-Python: >=3.7
License-File: LICENSE
